mycelyso/__init__.py
mycelyso/__main__.py
mycelyso/tunables.py
mycelyso/highlevel/__init__.py
mycelyso/highlevel/nodeframe.py
mycelyso/highlevel/pipeline.py
mycelyso/highlevel/pixelframe.py
mycelyso/highlevel/steps.py
mycelyso/misc/__init__.py
mycelyso/misc/graphml.py
mycelyso/misc/regression.py
mycelyso/misc/util.py
mycelyso/pilyso/__init__.py
mycelyso/pilyso/application/__init__.py
mycelyso/pilyso/application/application.py
mycelyso/pilyso/application/helper.py
mycelyso/pilyso/imagestack/__init__.py
mycelyso/pilyso/imagestack/imagestack.py
mycelyso/pilyso/imagestack/readers/__init__.py
mycelyso/pilyso/imagestack/readers/czi.py
mycelyso/pilyso/imagestack/readers/nd2.py
mycelyso/pilyso/imagestack/readers/ometiff.py
mycelyso/pilyso/imagestack/readers/tiff.py
mycelyso/pilyso/imagestack/readers/external/__init__.py
mycelyso/pilyso/imagestack/readers/external/czifile.py
mycelyso/pilyso/misc/__init__.py
mycelyso/pilyso/misc/h5writer.py
mycelyso/pilyso/misc/processpool.py
mycelyso/pilyso/misc/hacks/__init__.py
mycelyso/pilyso/misc/hacks/maintenance_interrupt.py
mycelyso/pilyso/misc/hacks/multiprocessing_patch.py
mycelyso/pilyso/misc/hacks/recursionlimit_raise.py
mycelyso/pilyso/pipeline/__init__.py
mycelyso/pilyso/pipeline/executor.py
mycelyso/pilyso/pipeline/pipeline.py
mycelyso/pilyso/steps/__init__.py
mycelyso/pilyso/steps/steps.py
mycelyso/processing/__init__.py
mycelyso/processing/binarization.py
mycelyso/processing/pixelgraphs.py
mycelyso/test/__init__.py
mycelyso/test/__main__.py
mycelyso-1.0.0.dist-info/LICENSE.rst
mycelyso-1.0.0.dist-info/METADATA
mycelyso-1.0.0.dist-info/WHEEL
mycelyso-1.0.0.dist-info/top_level.txt
mycelyso-1.0.0.dist-info/RECORD
